docformer/__init__.py
docformer/docformer.py
docformer-1.0.7.dist-info/METADATA
docformer-1.0.7.dist-info/WHEEL
docformer-1.0.7.dist-info/entry_points.txt
docformer-1.0.7.dist-info/top_level.txt
docformer-1.0.7.dist-info/RECORD
