Metadata-Version: 2.1
Name: docformer
Version: 1.0.7
Summary: A document editor for .docformer and .docform files
Home-page: https://github.com/yourusername/docformer
Author: Your Name
Author-email: your.email@example.com
Classifier: Programming Language :: Python :: 3
Classifier: License :: OSI Approved :: MIT License
Classifier: Operating System :: OS Independent
Requires-Python: >=3.6
